00_src/PHASE_ACCUMULATOR.sv
`timescale 1ns/1ps

module PHASE_ACCUMULATOR
#(
  PARA_COUNTER_WD = 32
)
(
  input logic                        I_CLK,
  input logic                        I_RESET_N,

  input logic                        I_PHASE_SAMPLE_EN,
  input logic [PARA_COUNTER_WD-1:0]  I_PHASE_FTW,
  input logic                        I_PHASE_CLEAR,

  output logic [PARA_COUNTER_WD-1:0] O_PHASE_COUNTER,
  output logic                       O_PHASE_FREQ_RANGE_ERROR
);

logic [PARA_COUNTER_WD-1:0] r_phase_counter;

assign O_PHASE_FREQ_RANGE_ERROR = (I_PHASE_FTW < 32'h000DA741) || (I_PHASE_FTW > 32'h35555555);

//=============================================================
//                      PHASE COUNTER
//=============================================================

always_ff @(posedge I_CLK or negedge I_RESET_N) begin
  if(!I_RESET_N)
    r_phase_counter <= 'h0;
  else if (I_PHASE_CLEAR)
    r_phase_counter <= 'h0;
  else if (I_PHASE_SAMPLE_EN) 
    r_phase_counter <= r_phase_counter + I_PHASE_FTW;
end

assign O_PHASE_COUNTER = r_phase_counter;

endmodule: PHASE_ACCUMULATOR

01_tb/PHASE_ACCUMULATOR_TB.sv
`timescale 1ns/1ps

module PHASE_ACCUMULATOR_TB;

localparam int COUNTER_WD = 32;
localparam logic [COUNTER_WD-1:0] MIN_FTW = 32'h000D_A741;
localparam logic [COUNTER_WD-1:0] MAX_FTW = 32'h3555_5555;

logic                  I_CLK;
logic                  I_RESET_N;
logic                  I_PHASE_SAMPLE_EN;
logic [COUNTER_WD-1:0] I_PHASE_FTW;
logic                  I_PHASE_CLEAR;
logic [COUNTER_WD-1:0] O_PHASE_COUNTER;
logic                  O_PHASE_FREQ_RANGE_ERROR;
int                    error_count;

PHASE_ACCUMULATOR #(.PARA_COUNTER_WD(COUNTER_WD)) dut (
  .I_CLK                    (I_CLK),
  .I_RESET_N                (I_RESET_N),
  .I_PHASE_SAMPLE_EN        (I_PHASE_SAMPLE_EN),
  .I_PHASE_FTW              (I_PHASE_FTW),
  .I_PHASE_CLEAR            (I_PHASE_CLEAR),
  .O_PHASE_COUNTER          (O_PHASE_COUNTER),
  .O_PHASE_FREQ_RANGE_ERROR (O_PHASE_FREQ_RANGE_ERROR)
);

/* verilator lint_off BLKSEQ */
always #5 I_CLK = ~I_CLK;
/* verilator lint_on BLKSEQ */

task automatic check_counter(input logic [COUNTER_WD-1:0] expected,
                             input string test_name);
begin
  if (O_PHASE_COUNTER !== expected) begin
    $error("FAIL: %s, counter=0x%08h, expected=0x%08h",
           test_name, O_PHASE_COUNTER, expected);
    error_count++;
  end else
    $display("PASS: %s", test_name);
end
endtask

task automatic check_range_error(input logic expected,
                                 input string test_name);
begin
  #1;
  if (O_PHASE_FREQ_RANGE_ERROR !== expected) begin
    $error("FAIL: %s, range_error=%0b, expected=%0b",
           test_name, O_PHASE_FREQ_RANGE_ERROR, expected);
    error_count++;
  end else
    $display("PASS: %s", test_name);
end
endtask

task automatic apply_reset;
begin
  @(negedge I_CLK);
  I_RESET_N         = 1'b0;
  I_PHASE_SAMPLE_EN = 1'b0;
  I_PHASE_CLEAR     = 1'b0;
  #1;
  check_counter('0, "Asynchronous active-low reset");
  repeat (2) @(negedge I_CLK);
  I_RESET_N = 1'b1;
  @(posedge I_CLK);
  #1;
  check_counter('0, "Counter remains zero after reset release");
end
endtask

task automatic test_enable_and_hold;
  logic [COUNTER_WD-1:0] expected;
begin
  $display("\nTEST 1: Sample enable and hold");
  apply_reset();
  expected = '0;
  @(negedge I_CLK);
  I_PHASE_FTW       = MIN_FTW;
  I_PHASE_SAMPLE_EN = 1'b1;
  repeat (4) begin
    @(posedge I_CLK);
    expected = expected + MIN_FTW;
    #1;
    check_counter(expected, "Counter accumulates FTW when enabled");
  end
  @(negedge I_CLK);
  I_PHASE_SAMPLE_EN = 1'b0;
  repeat (3) begin
    @(posedge I_CLK);
    #1;
    check_counter(expected, "Counter holds when sample enable is low");
  end
end
endtask

task automatic test_clear_priority;
begin
  $display("\nTEST 2: Synchronous clear and priority");
  apply_reset();
  @(negedge I_CLK);
  I_PHASE_FTW       = 32'h0123_4567;
  I_PHASE_SAMPLE_EN = 1'b1;
  repeat (2) @(posedge I_CLK);
  @(negedge I_CLK);
  I_PHASE_CLEAR = 1'b1;
  @(posedge I_CLK);
  #1;
  check_counter('0, "Clear has priority over accumulation");
  @(negedge I_CLK);
  I_PHASE_CLEAR = 1'b0;
  @(posedge I_CLK);
  #1;
  check_counter(32'h0123_4567, "Accumulation resumes after clear");
end
endtask

task automatic test_counter_wrap;
  logic [COUNTER_WD-1:0] expected;
  int index;
begin
  $display("\nTEST 3: Natural modulo wrap-around");
  apply_reset();
  expected = '0;
  @(negedge I_CLK);
  I_PHASE_FTW       = MAX_FTW;
  I_PHASE_SAMPLE_EN = 1'b1;
  for (index = 0; index < 6; index++) begin
    @(posedge I_CLK);
    expected = expected + MAX_FTW;
    #1;
    check_counter(expected, "Counter wraps at configured width");
  end
end
endtask

task automatic test_ftw_range;
begin
  $display("\nTEST 4: FTW range checking");
  I_PHASE_FTW = MIN_FTW - 1'b1;
  check_range_error(1'b1, "FTW below minimum is rejected");
  I_PHASE_FTW = MIN_FTW;
  check_range_error(1'b0, "Minimum FTW is accepted");
  I_PHASE_FTW = MIN_FTW + 1'b1;
  check_range_error(1'b0, "FTW inside range is accepted");
  I_PHASE_FTW = MAX_FTW - 1'b1;
  check_range_error(1'b0, "FTW below maximum is accepted");
  I_PHASE_FTW = MAX_FTW;
  check_range_error(1'b0, "Maximum FTW is accepted");
  I_PHASE_FTW = MAX_FTW + 1'b1;
  check_range_error(1'b1, "FTW above maximum is rejected");
end
endtask

initial begin
  I_CLK             = 1'b0;
  I_RESET_N         = 1'b0;
  I_PHASE_SAMPLE_EN = 1'b0;
  I_PHASE_FTW       = MIN_FTW;
  I_PHASE_CLEAR     = 1'b0;
  error_count       = 0;
  $dumpfile("PHASE_ACCUMULATOR_TB.vcd");
  $dumpvars(0, PHASE_ACCUMULATOR_TB);
  test_enable_and_hold();
  test_clear_priority();
  test_counter_wrap();
  test_ftw_range();
  if (error_count == 0)
    $display("\nALL TESTS PASSED");
  else
    $fatal(1, "\nTEST FAILED: %0d error(s)", error_count);
  $finish;
end

endmodule: PHASE_ACCUMULATOR_TB

PHASE_ACCUMULATOR_TB.vcd
$date
	Tue Sep  1 21:15:52 2026
$end
$version
	Icarus Verilog
$end
$timescale
	1ps
$end
$scope module PHASE_ACCUMULATOR_TB $end
$var wire 1 ! O_PHASE_FREQ_RANGE_ERROR $end
$var wire 32 " O_PHASE_COUNTER [31:0] $end
$var parameter 32 # COUNTER_WD $end
$var parameter 32 $ MAX_FTW $end
$var parameter 32 % MIN_FTW $end
$var reg 1 & I_CLK $end
$var reg 1 ' I_PHASE_CLEAR $end
$var reg 32 ( I_PHASE_FTW [31:0] $end
$var reg 1 ) I_PHASE_SAMPLE_EN $end
$var reg 1 * I_RESET_N $end
$var integer 32 + error_count [31:0] $end
$scope module dut $end
$var wire 1 & I_CLK $end
$var wire 1 ' I_PHASE_CLEAR $end
$var wire 32 , I_PHASE_FTW [31:0] $end
$var wire 1 ) I_PHASE_SAMPLE_EN $end
$var wire 1 * I_RESET_N $end
$var wire 32 - O_PHASE_COUNTER [31:0] $end
$var wire 1 ! O_PHASE_FREQ_RANGE_ERROR $end
$var parameter 32 . PARA_COUNTER_WD $end
$var reg 32 / r_phase_counter [31:0] $end
$upscope $end
$scope task apply_reset $end
$upscope $end
$scope task check_counter $end
$upscope $end
$scope task check_range_error $end
$upscope $end
$scope task test_clear_priority $end
$upscope $end
$scope task test_counter_wrap $end
$upscope $end
$scope task test_enable_and_hold $end
$upscope $end
$scope task test_ftw_range $end
$upscope $end
$upscope $end
$enddefinitions $end
$comment Show the parameter values. $end
$dumpall
b100000 .
b11011010011101000001 %
b110101010101010101010101010101 $
b100000 #
$end
#0
$dumpvars
b0 /
b0 -
b11011010011101000001 ,
b0 +
0*
0)
b11011010011101000001 (
0'
0&
b0 "
0!
$end
#5000
1&
#10000
0&
#15000
1&
#20000
0&
#25000
1&
#30000
1*
0&
#35000
1&
#40000
1)
0&
#45000
b11011010011101000001 "
b11011010011101000001 -
b11011010011101000001 /
1&
#50000
0&
#55000
b110110100111010000010 "
b110110100111010000010 -
b110110100111010000010 /
1&
#60000
0&
#65000
b1010001111010111000011 "
b1010001111010111000011 -
b1010001111010111000011 /
1&
#70000
0&
#75000
b1101101001110100000100 "
b1101101001110100000100 -
b1101101001110100000100 /
1&
#80000
0)
0&
#85000
1&
#90000
0&
#95000
1&
#100000
0&
#105000
1&
#110000
b0 "
b0 -
b0 /
0*
0&
#115000
1&
#120000
0&
#125000
1&
#130000
1*
0&
#135000
1&
#140000
1)
b1001000110100010101100111 (
b1001000110100010101100111 ,
0&
#145000
b1001000110100010101100111 "
b1001000110100010101100111 -
b1001000110100010101100111 /
1&
#150000
0&
#155000
b10010001101000101011001110 "
b10010001101000101011001110 -
b10010001101000101011001110 /
1&
#160000
1'
0&
#165000
b0 "
b0 -
b0 /
1&
#170000
0'
0&
#175000
b1001000110100010101100111 "
b1001000110100010101100111 -
b1001000110100010101100111 /
1&
#180000
b0 "
b0 -
b0 /
0)
0*
0&
#185000
1&
#190000
0&
#195000
1&
#200000
1*
0&
#205000
1&
#210000
1)
b110101010101010101010101010101 (
b110101010101010101010101010101 ,
0&
#215000
b110101010101010101010101010101 "
b110101010101010101010101010101 -
b110101010101010101010101010101 /
1&
#220000
0&
#225000
b1101010101010101010101010101010 "
b1101010101010101010101010101010 -
b1101010101010101010101010101010 /
1&
#230000
0&
#235000
b10011111111111111111111111111111 "
b10011111111111111111111111111111 -
b10011111111111111111111111111111 /
1&
#240000
0&
#245000
b11010101010101010101010101010100 "
b11010101010101010101010101010100 -
b11010101010101010101010101010100 /
1&
#250000
0&
#255000
b1010101010101010101010101001 "
b1010101010101010101010101001 -
b1010101010101010101010101001 /
1&
#260000
0&
#265000
b111111111111111111111111111110 "
b111111111111111111111111111110 -
b111111111111111111111111111110 /
1&
#266000
1!
b11011010011101000000 (
b11011010011101000000 ,
#267000
0!
b11011010011101000001 (
b11011010011101000001 ,
#268000
b11011010011101000010 (
b11011010011101000010 ,
#269000
b110101010101010101010101010100 (
b110101010101010101010101010100 ,
#270000
b110101010101010101010101010101 (
b110101010101010101010101010101 ,
0&
#271000
1!
b110101010101010101010101010110 (
b110101010101010101010101010110 ,
