00_src/PHASE_ACCUMULATOR.sv
`timescale 1ns/1ps

module PHASE_ACCUMULATOR
#(
  PARA_COUNTER_WD = 32
)
(
  input logic                        I_CLK,
  input logic                        I_RESET_N,

  input logic                        I_PHASE_SAMPLE_EN,
  input logic [PARA_COUNTER_WD-1:0]  I_PHASE_FTW,
  input logic                        I_PHASE_CLEAR,

  output logic [PARA_COUNTER_WD-1:0] O_PHASE_COUNTER,
  output logic                       O_PHASE_FREQ_RANGE_ERROR
);

logic [PARA_COUNTER_WD-1:0] r_phase_counter;

assign O_PHASE_FREQ_RANGE_ERROR = (I_PHASE_FTW < 32'h000DA741) || (I_PHASE_FTW > 32'h35555555);

//=============================================================
//                      PHASE COUNTER
//=============================================================

always_ff @(posedge I_CLK or negedge I_RESET_N) begin
  if(!I_RESET_N)
    r_phase_counter <= 'h0;
  else if (I_PHASE_CLEAR)
    r_phase_counter <= 'h0;
  else if (I_PHASE_SAMPLE_EN) 
    r_phase_counter <= r_phase_counter + I_PHASE_FTW;
end

assign O_PHASE_COUNTER = r_phase_counter;

endmodule: PHASE_ACCUMULATOR

01_tb/PHASE_ACCUMULATOR_TB.sv
`timescale 1ns/1ps

module PHASE_ACCUMULATOR_TB;

localparam int COUNTER_WD = 32;
localparam logic [COUNTER_WD-1:0] MIN_FTW = 32'h000D_A741;
localparam logic [COUNTER_WD-1:0] MAX_FTW = 32'h3555_5555;

logic                  I_CLK;
logic                  I_RESET_N;
logic                  I_PHASE_SAMPLE_EN;
logic [COUNTER_WD-1:0] I_PHASE_FTW;
logic                  I_PHASE_CLEAR;
logic [COUNTER_WD-1:0] O_PHASE_COUNTER;
logic                  O_PHASE_FREQ_RANGE_ERROR;
int                    error_count;

PHASE_ACCUMULATOR #(.PARA_COUNTER_WD(COUNTER_WD)) dut (
  .I_CLK                    (I_CLK),
  .I_RESET_N                (I_RESET_N),
  .I_PHASE_SAMPLE_EN        (I_PHASE_SAMPLE_EN),
  .I_PHASE_FTW              (I_PHASE_FTW),
  .I_PHASE_CLEAR            (I_PHASE_CLEAR),
  .O_PHASE_COUNTER          (O_PHASE_COUNTER),
  .O_PHASE_FREQ_RANGE_ERROR (O_PHASE_FREQ_RANGE_ERROR)
);

/* verilator lint_off BLKSEQ */
always #5 I_CLK = ~I_CLK;
/* verilator lint_on BLKSEQ */

task automatic check_counter(input logic [COUNTER_WD-1:0] expected,
                             input string test_name);
begin
  if (O_PHASE_COUNTER !== expected) begin
    $error("FAIL: %s, counter=0x%08h, expected=0x%08h",
           test_name, O_PHASE_COUNTER, expected);
    error_count++;
  end else
    $display("PASS: %s", test_name);
end
endtask

task automatic check_range_error(input logic expected,
                                 input string test_name);
begin
  #1;
  if (O_PHASE_FREQ_RANGE_ERROR !== expected) begin
    $error("FAIL: %s, range_error=%0b, expected=%0b",
           test_name, O_PHASE_FREQ_RANGE_ERROR, expected);
    error_count++;
  end else
    $display("PASS: %s", test_name);
end
endtask

task automatic apply_reset;
begin
  @(negedge I_CLK);
  I_RESET_N         = 1'b0;
  I_PHASE_SAMPLE_EN = 1'b0;
  I_PHASE_CLEAR     = 1'b0;
  #1;
  check_counter('0, "Asynchronous active-low reset");
  repeat (2) @(negedge I_CLK);
  I_RESET_N = 1'b1;
  @(posedge I_CLK);
  #1;
  check_counter('0, "Counter remains zero after reset release");
end
endtask

task automatic test_enable_and_hold;
  logic [COUNTER_WD-1:0] expected;
begin
  $display("\nTEST 1: Sample enable and hold");
  apply_reset();
  expected = '0;
  @(negedge I_CLK);
  I_PHASE_FTW       = MIN_FTW;
  I_PHASE_SAMPLE_EN = 1'b1;
  repeat (4) begin
    @(posedge I_CLK);
    expected = expected + MIN_FTW;
    #1;
    check_counter(expected, "Counter accumulates FTW when enabled");
  end
  @(negedge I_CLK);
  I_PHASE_SAMPLE_EN = 1'b0;
  repeat (3) begin
    @(posedge I_CLK);
    #1;
    check_counter(expected, "Counter holds when sample enable is low");
  end
end
endtask

task automatic test_clear_priority;
begin
  $display("\nTEST 2: Synchronous clear and priority");
  apply_reset();
  @(negedge I_CLK);
  I_PHASE_FTW       = 32'h0123_4567;
  I_PHASE_SAMPLE_EN = 1'b1;
  repeat (2) @(posedge I_CLK);
  @(negedge I_CLK);
  I_PHASE_CLEAR = 1'b1;
  @(posedge I_CLK);
  #1;
  check_counter('0, "Clear has priority over accumulation");
  @(negedge I_CLK);
  I_PHASE_CLEAR = 1'b0;
  @(posedge I_CLK);
  #1;
  check_counter(32'h0123_4567, "Accumulation resumes after clear");
end
endtask

task automatic test_counter_wrap;
  logic [COUNTER_WD-1:0] expected;
  int index;
begin
  $display("\nTEST 3: Natural modulo wrap-around");
  apply_reset();
  expected = '0;
  @(negedge I_CLK);
  I_PHASE_FTW       = MAX_FTW;
  I_PHASE_SAMPLE_EN = 1'b1;
  for (index = 0; index < 6; index++) begin
    @(posedge I_CLK);
    expected = expected + MAX_FTW;
    #1;
    check_counter(expected, "Counter wraps at configured width");
  end
end
endtask

task automatic test_ftw_range;
begin
  $display("\nTEST 4: FTW range checking");
  I_PHASE_FTW = MIN_FTW - 1'b1;
  check_range_error(1'b1, "FTW below minimum is rejected");
  I_PHASE_FTW = MIN_FTW;
  check_range_error(1'b0, "Minimum FTW is accepted");
  I_PHASE_FTW = MIN_FTW + 1'b1;
  check_range_error(1'b0, "FTW inside range is accepted");
  I_PHASE_FTW = MAX_FTW - 1'b1;
  check_range_error(1'b0, "FTW below maximum is accepted");
  I_PHASE_FTW = MAX_FTW;
  check_range_error(1'b0, "Maximum FTW is accepted");
  I_PHASE_FTW = MAX_FTW + 1'b1;
  check_range_error(1'b1, "FTW above maximum is rejected");
end
endtask

initial begin
  I_CLK             = 1'b0;
  I_RESET_N         = 1'b0;
  I_PHASE_SAMPLE_EN = 1'b0;
  I_PHASE_FTW       = MIN_FTW;
  I_PHASE_CLEAR     = 1'b0;
  error_count       = 0;
  $dumpfile("PHASE_ACCUMULATOR_TB.vcd");
  $dumpvars(0, PHASE_ACCUMULATOR_TB);
  test_enable_and_hold();
  test_clear_priority();
  test_counter_wrap();
  test_ftw_range();
  if (error_count == 0)
    $display("\nALL TESTS PASSED");
  else
    $fatal(1, "\nTEST FAILED: %0d error(s)", error_count);
  $finish;
end

endmodule: PHASE_ACCUMULATOR_TB

02_sim/run/PHASE_ACCUMULATOR_TB/PHASE_ACCUMULATOR_TB.vcd
$version Generated by VerilatedVcd $end
$timescale 1ps $end
 $scope module TOP $end
  $scope module PHASE_ACCUMULATOR_TB $end
   $var wire 32 + COUNTER_WD [31:0] $end
   $var wire 32 , MIN_FTW [31:0] $end
   $var wire 32 - MAX_FTW [31:0] $end
   $var wire 1 ) I_CLK $end
   $var wire 1 # I_RESET_N $end
   $var wire 1 $ I_PHASE_SAMPLE_EN $end
   $var wire 32 % I_PHASE_FTW [31:0] $end
   $var wire 1 & I_PHASE_CLEAR $end
   $var wire 32 * O_PHASE_COUNTER [31:0] $end
   $var wire 1 ' O_PHASE_FREQ_RANGE_ERROR $end
   $var wire 32 ( error_count [31:0] $end
   $scope module dut $end
    $var wire 32 . PARA_COUNTER_WD [31:0] $end
    $var wire 1 ) I_CLK $end
    $var wire 1 # I_RESET_N $end
    $var wire 1 $ I_PHASE_SAMPLE_EN $end
    $var wire 32 % I_PHASE_FTW [31:0] $end
    $var wire 1 & I_PHASE_CLEAR $end
    $var wire 32 * O_PHASE_COUNTER [31:0] $end
    $var wire 1 ' O_PHASE_FREQ_RANGE_ERROR $end
    $var wire 32 * r_phase_counter [31:0] $end
   $upscope $end
  $upscope $end
 $upscope $end
$enddefinitions $end


#0
0#
0$
b00000000000011011010011101000001 %
0&
0'
b00000000000000000000000000000000 (
0)
b00000000000000000000000000000000 *
b00000000000000000000000000100000 +
b00000000000011011010011101000001 ,
b00110101010101010101010101010101 -
b00000000000000000000000000100000 .
#5000
1)
#10000
0)
#11000
#15000
1)
#20000
0)
#25000
1)
#30000
1#
0)
#35000
1)
#36000
#40000
1$
0)
#45000
1)
b00000000000011011010011101000001 *
#46000
#50000
0)
#55000
1)
b00000000000110110100111010000010 *
#56000
#60000
0)
#65000
1)
b00000000001010001111010111000011 *
#66000
#70000
0)
#75000
1)
b00000000001101101001110100000100 *
#76000
#80000
0$
0)
#85000
1)
#86000
#90000
0)
#95000
1)
#96000
#100000
0)
#105000
1)
#106000
#110000
0#
0)
b00000000000000000000000000000000 *
#111000
#115000
1)
#120000
0)
#125000
1)
#130000
1#
0)
#135000
1)
#136000
#140000
1$
b00000001001000110100010101100111 %
0)
#145000
1)
b00000001001000110100010101100111 *
#150000
0)
#155000
1)
b00000010010001101000101011001110 *
#160000
1&
0)
#165000
1)
b00000000000000000000000000000000 *
#166000
#170000
0&
0)
#175000
1)
b00000001001000110100010101100111 *
#176000
#180000
0#
0$
0)
b00000000000000000000000000000000 *
#181000
#185000
1)
#190000
0)
#195000
1)
#200000
1#
0)
#205000
1)
#206000
#210000
1$
b00110101010101010101010101010101 %
0)
#215000
1)
b00110101010101010101010101010101 *
#216000
#220000
0)
#225000
1)
b01101010101010101010101010101010 *
#226000
#230000
0)
#235000
1)
b10011111111111111111111111111111 *
#236000
#240000
0)
#245000
1)
b11010101010101010101010101010100 *
#246000
#250000
0)
#255000
1)
b00001010101010101010101010101001 *
#256000
#260000
0)
#265000
1)
b00111111111111111111111111111110 *
#266000
b00000000000011011010011101000000 %
1'
#267000
b00000000000011011010011101000001 %
0'
#268000
b00000000000011011010011101000010 %
#269000
b00110101010101010101010101010100 %
#270000
b00110101010101010101010101010101 %
0)
#271000
b00110101010101010101010101010110 %
1'
